testoli/__init__.py
testoli/test.py
testoli/test.txt
testoli-0.1.1.dist-info/WHEEL
testoli-0.1.1.dist-info/entry_points.txt
testoli-0.1.1.dist-info/METADATA
testoli-0.1.1.dist-info/RECORD
