Metadata-Version: 2.3
Name: testoli
Version: 0.1.1
Summary: Add your description here
Requires-Dist: rich>=13.8.1
Requires-Python: >=3.7
